{
  "currentPage": 585,
  "totalItems": 21025,
  "totalPages": 841,
  "items": [
    {
      "id": 344848019,
      "eventId": 569872,
      "siteUnitNumber": 12616,
      "bathingSite": "GURNARD",
      "eventStart": "2022-03-16T12:57:48",
      "eventStop": "2022-03-16T17:03:00",
      "duration": 245,
      "status": "Genuine",
      "associatedSiteId": 110701,
      "outfallName": "TERMINUS ROAD COWES 2",
      "isImpacting": true,
      "overFlowSiteId": 0,
      "historicSpillsList": [
        {
          "id": 344848019,
          "eventId": 569872,
          "siteUnitNumber": 12616,
          "bathingSite": "GURNARD",
          "eventStart": "2022-03-16T12:57:48",
          "eventStop": "2022-03-16T17:03:00",
          "duration": 245,
          "status": "Genuine",
          "associatedSiteId": 110701,
          "outfallName": "TERMINUS ROAD COWES 2",
          "isImpacting": true,
          "overFlowSiteId": 108563
        },
        {
          "id": 344848020,
          "eventId": 569872,
          "siteUnitNumber": 12617,
          "bathingSite": "COWES",
          "eventStart": "2022-03-16T12:57:48",
          "eventStop": "2022-03-16T17:03:00",
          "duration": 245,
          "status": "Genuine",
          "associatedSiteId": 110701,
          "outfallName": "TERMINUS ROAD COWES 2",
          "isImpacting": true,
          "overFlowSiteId": 108563,
          "historicSpillsList": []
        }
      ]
    },
    {
      "id": 344848017,
      "eventId": 569976,
      "siteUnitNumber": 12616,
      "bathingSite": "GURNARD",
      "eventStart": "2022-03-16T13:06:00",
      "eventStop": "2022-03-16T16:56:00",
      "duration": 230,
      "status": "Genuine",
      "associatedSiteId": 110701,
      "outfallName": "TERMINUS ROAD COWES 2",
      "isImpacting": true,
      "overFlowSiteId": 0,
      "historicSpillsList": [
        {
          "id": 344848017,
          "eventId": 569976,
          "siteUnitNumber": 12616,
          "bathingSite": "GURNARD",
          "eventStart": "2022-03-16T13:06:00",
          "eventStop": "2022-03-16T16:56:00",
          "duration": 230,
          "status": "Genuine",
          "associatedSiteId": 110701,
          "outfallName": "TERMINUS ROAD COWES 2",
          "isImpacting": true,
          "overFlowSiteId": 108562
        },
        {
          "id": 344848018,
          "eventId": 569976,
          "siteUnitNumber": 12617,
          "bathingSite": "COWES",
          "eventStart": "2022-03-16T13:06:00",
          "eventStop": "2022-03-16T16:56:00",
          "duration": 230,
          "status": "Genuine",
          "associatedSiteId": 110701,
          "outfallName": "TERMINUS ROAD COWES 2",
          "isImpacting": true,
          "overFlowSiteId": 108562,
          "historicSpillsList": []
        }
      ]
    },
    {
      "id": 344819980,
      "eventId": 570002,
      "siteUnitNumber": 12607,
      "bathingSite": "HILLHEAD",
      "eventStart": "2022-03-16T15:21:52",
      "eventStop": "2022-03-16T16:49:00",
      "duration": 87,
      "status": "Genuine",
      "associatedSiteId": 109751,
      "outfallName": "HOOK PARK NO.1",
      "isImpacting": true,
      "overFlowSiteId": 0,
      "historicSpillsList": [
        {
          "id": 344819980,
          "eventId": 570002,
          "siteUnitNumber": 12607,
          "bathingSite": "HILLHEAD",
          "eventStart": "2022-03-16T15:21:52",
          "eventStop": "2022-03-16T16:49:00",
          "duration": 87,
          "status": "Genuine",
          "associatedSiteId": 109751,
          "outfallName": "HOOK PARK NO.1",
          "isImpacting": true,
          "overFlowSiteId": 111291
        }
      ]
    },
    {
      "id": 344823007,
      "eventId": 570046,
      "siteUnitNumber": 12661,
      "bathingSite": "LANGSTONE HARBOUR",
      "eventStart": "2022-03-16T16:14:00",
      "eventStop": "2022-03-16T16:35:00",
      "duration": 21,
      "status": "Genuine",
      "associatedSiteId": 109819,
      "outfallName": "COURT LANE COSHAM",
      "isImpacting": true,
      "overFlowSiteId": 0,
      "historicSpillsList": [
        {
          "id": 344823007,
          "eventId": 570046,
          "siteUnitNumber": 12661,
          "bathingSite": "LANGSTONE HARBOUR",
          "eventStart": "2022-03-16T16:14:00",
          "eventStop": "2022-03-16T16:35:00",
          "duration": 21,
          "status": "Genuine",
          "associatedSiteId": 109819,
          "outfallName": "COURT LANE COSHAM",
          "isImpacting": true,
          "overFlowSiteId": 115958
        }
      ]
    },
    {
      "id": 344848738,
      "eventId": 569964,
      "siteUnitNumber": 12620,
      "bathingSite": "ST HELENS",
      "eventStart": "2022-03-16T14:19:30",
      "eventStop": "2022-03-16T16:26:33",
      "duration": 127,
      "status": "Genuine",
      "associatedSiteId": 110761,
      "outfallName": "BRADING",
      "isImpacting": true,
      "overFlowSiteId": 0,
      "historicSpillsList": [
        {
          "id": 344848738,
          "eventId": 569964,
          "siteUnitNumber": 12620,
          "bathingSite": "ST HELENS",
          "eventStart": "2022-03-16T14:19:30",
          "eventStop": "2022-03-16T16:26:33",
          "duration": 127,
          "status": "Genuine",
          "associatedSiteId": 110761,
          "outfallName": "BRADING",
          "isImpacting": true,
          "overFlowSiteId": 113676
        }
      ]
    },
    {
      "id": 344836537,
      "eventId": 569996,
      "siteUnitNumber": 12594,
      "bathingSite": "BOGNOR REGIS EAST",
      "eventStart": "2022-03-16T15:30:00",
      "eventStop": "2022-03-16T16:21:00",
      "duration": 51,
      "status": "Genuine",
      "associatedSiteId": 109959,
      "outfallName": "WEST PARK BOGNOR REGIS",
      "isImpacting": true,
      "overFlowSiteId": 0,
      "historicSpillsList": [
        {
          "id": 344836537,
          "eventId": 569996,
          "siteUnitNumber": 12594,
          "bathingSite": "BOGNOR REGIS EAST",
          "eventStart": "2022-03-16T15:30:00",
          "eventStop": "2022-03-16T16:21:00",
          "duration": 51,
          "status": "Genuine",
          "associatedSiteId": 109959,
          "outfallName": "WEST PARK BOGNOR REGIS",
          "isImpacting": true,
          "overFlowSiteId": 108160
        },
        {
          "id": 344836538,
          "eventId": 569996,
          "siteUnitNumber": 12595,
          "bathingSite": "BOGNOR REGIS (ALDWICK)",
          "eventStart": "2022-03-16T15:30:00",
          "eventStop": "2022-03-16T16:21:00",
          "duration": 51,
          "status": "Genuine",
          "associatedSiteId": 109959,
          "outfallName": "WEST PARK BOGNOR REGIS",
          "isImpacting": true,
          "overFlowSiteId": 108160,
          "historicSpillsList": []
        },
        {
          "id": 344836539,
          "eventId": 569996,
          "siteUnitNumber": 12596,
          "bathingSite": "PAGHAM",
          "eventStart": "2022-03-16T15:30:00",
          "eventStop": "2022-03-16T16:21:00",
          "duration": 51,
          "status": "Genuine",
          "associatedSiteId": 109959,
          "outfallName": "WEST PARK BOGNOR REGIS",
          "isImpacting": true,
          "overFlowSiteId": 108160,
          "historicSpillsList": []
        }
      ]
    },
    {
      "id": 344814875,
      "eventId": 570053,
      "siteUnitNumber": 12614,
      "bathingSite": "TOTLAND BAY",
      "eventStart": "2022-03-16T13:26:00",
      "eventStop": "2022-03-16T16:21:00",
      "duration": 175,
      "status": "Genuine",
      "associatedSiteId": 109657,
      "outfallName": "THE PROMENADE TOTLAND PIER NO2",
      "isImpacting": true,
      "overFlowSiteId": 0,
      "historicSpillsList": [
        {
          "id": 344814875,
          "eventId": 570053,
          "siteUnitNumber": 12614,
          "bathingSite": "TOTLAND BAY",
          "eventStart": "2022-03-16T13:26:00",
          "eventStop": "2022-03-16T16:21:00",
          "duration": 175,
          "status": "Genuine",
          "associatedSiteId": 109657,
          "outfallName": "THE PROMENADE TOTLAND PIER NO2",
          "isImpacting": true,
          "overFlowSiteId": 115944
        },
        {
          "id": 344814876,
          "eventId": 570053,
          "siteUnitNumber": 12615,
          "bathingSite": "COLWELL BAY",
          "eventStart": "2022-03-16T13:26:00",
          "eventStop": "2022-03-16T16:21:00",
          "duration": 175,
          "status": "Genuine",
          "associatedSiteId": 109657,
          "outfallName": "THE PROMENADE TOTLAND PIER NO2",
          "isImpacting": true,
          "overFlowSiteId": 115944,
          "historicSpillsList": []
        }
      ]
    },
    {
      "id": 344823652,
      "eventId": 569947,
      "siteUnitNumber": 12604,
      "bathingSite": "SOUTHSEA EAST",
      "eventStart": "2022-03-16T14:24:00",
      "eventStop": "2022-03-16T16:20:00",
      "duration": 116,
      "status": "Genuine",
      "associatedSiteId": 109822,
      "outfallName": "PIER ROAD SOUTHSEA",
      "isImpacting": true,
      "overFlowSiteId": 0,
      "historicSpillsList": [
        {
          "id": 344823652,
          "eventId": 569947,
          "siteUnitNumber": 12604,
          "bathingSite": "SOUTHSEA EAST",
          "eventStart": "2022-03-16T14:24:00",
          "eventStop": "2022-03-16T16:20:00",
          "duration": 116,
          "status": "Genuine",
          "associatedSiteId": 109822,
          "outfallName": "PIER ROAD SOUTHSEA",
          "isImpacting": true,
          "overFlowSiteId": 108469
        },
        {
          "id": 344823653,
          "eventId": 569947,
          "siteUnitNumber": 12605,
          "bathingSite": "STOKES BAY",
          "eventStart": "2022-03-16T14:24:00",
          "eventStop": "2022-03-16T16:20:00",
          "duration": 116,
          "status": "Genuine",
          "associatedSiteId": 109822,
          "outfallName": "PIER ROAD SOUTHSEA",
          "isImpacting": true,
          "overFlowSiteId": 108469,
          "historicSpillsList": []
        }
      ]
    },
    {
      "id": 344817605,
      "eventId": 569889,
      "siteUnitNumber": 12616,
      "bathingSite": "GURNARD",
      "eventStart": "2022-03-16T13:17:00",
      "eventStop": "2022-03-16T16:06:00",
      "duration": 169,
      "status": "Genuine",
      "associatedSiteId": 109704,
      "outfallName": "EGYPT POINT COWES",
      "isImpacting": true,
      "overFlowSiteId": 0,
      "historicSpillsList": [
        {
          "id": 344817605,
          "eventId": 569889,
          "siteUnitNumber": 12616,
          "bathingSite": "GURNARD",
          "eventStart": "2022-03-16T13:17:00",
          "eventStop": "2022-03-16T16:06:00",
          "duration": 169,
          "status": "Genuine",
          "associatedSiteId": 109704,
          "outfallName": "EGYPT POINT COWES",
          "isImpacting": true,
          "overFlowSiteId": 116213
        },
        {
          "id": 344817606,
          "eventId": 569889,
          "siteUnitNumber": 12617,
          "bathingSite": "COWES",
          "eventStart": "2022-03-16T13:17:00",
          "eventStop": "2022-03-16T16:06:00",
          "duration": 169,
          "status": "Genuine",
          "associatedSiteId": 109704,
          "outfallName": "EGYPT POINT COWES",
          "isImpacting": true,
          "overFlowSiteId": 116213,
          "historicSpillsList": []
        }
      ]
    },
    {
      "id": 344837907,
      "eventId": 570020,
      "siteUnitNumber": 12591,
      "bathingSite": "LITTLEHAMPTON",
      "eventStart": "2022-03-16T15:37:00",
      "eventStop": "2022-03-16T16:04:00",
      "duration": 27,
      "status": "Genuine",
      "associatedSiteId": 109968,
      "outfallName": "FORD ROAD ARUNDEL",
      "isImpacting": true,
      "overFlowSiteId": 0,
      "historicSpillsList": [
        {
          "id": 344837907,
          "eventId": 570020,
          "siteUnitNumber": 12591,
          "bathingSite": "LITTLEHAMPTON",
          "eventStart": "2022-03-16T15:37:00",
          "eventStop": "2022-03-16T16:04:00",
          "duration": 27,
          "status": "Genuine",
          "associatedSiteId": 109968,
          "outfallName": "FORD ROAD ARUNDEL",
          "isImpacting": true,
          "overFlowSiteId": 108002
        }
      ]
    },
    {
      "id": 344817119,
      "eventId": 569915,
      "siteUnitNumber": 12616,
      "bathingSite": "GURNARD",
      "eventStart": "2022-03-16T13:45:00",
      "eventStop": "2022-03-16T15:48:00",
      "duration": 123,
      "status": "Genuine",
      "associatedSiteId": 109702,
      "outfallName": "ALBANY ROAD EAST COWES",
      "isImpacting": true,
      "overFlowSiteId": 0,
      "historicSpillsList": [
        {
          "id": 344817119,
          "eventId": 569915,
          "siteUnitNumber": 12616,
          "bathingSite": "GURNARD",
          "eventStart": "2022-03-16T13:45:00",
          "eventStop": "2022-03-16T15:48:00",
          "duration": 123,
          "status": "Genuine",
          "associatedSiteId": 109702,
          "outfallName": "ALBANY ROAD EAST COWES",
          "isImpacting": true,
          "overFlowSiteId": 116071
        },
        {
          "id": 344817120,
          "eventId": 569915,
          "siteUnitNumber": 12617,
          "bathingSite": "COWES",
          "eventStart": "2022-03-16T13:45:00",
          "eventStop": "2022-03-16T15:48:00",
          "duration": 123,
          "status": "Genuine",
          "associatedSiteId": 109702,
          "outfallName": "ALBANY ROAD EAST COWES",
          "isImpacting": true,
          "overFlowSiteId": 116071,
          "historicSpillsList": []
        }
      ]
    },
    {
      "id": 344815198,
      "eventId": 569943,
      "siteUnitNumber": 12615,
      "bathingSite": "COLWELL BAY",
      "eventStart": "2022-03-16T14:09:00",
      "eventStop": "2022-03-16T14:33:00",
      "duration": 24,
      "status": "Genuine",
      "associatedSiteId": 109665,
      "outfallName": "THORLEY ROAD BOULDNOR",
      "isImpacting": true,
      "overFlowSiteId": 0,
      "historicSpillsList": [
        {
          "id": 344815198,
          "eventId": 569943,
          "siteUnitNumber": 12615,
          "bathingSite": "COLWELL BAY",
          "eventStart": "2022-03-16T14:09:00",
          "eventStop": "2022-03-16T14:33:00",
          "duration": 24,
          "status": "Genuine",
          "associatedSiteId": 109665,
          "outfallName": "THORLEY ROAD BOULDNOR",
          "isImpacting": true,
          "overFlowSiteId": 110277
        },
        {
          "id": 344815199,
          "eventId": 569943,
          "siteUnitNumber": 12614,
          "bathingSite": "TOTLAND BAY",
          "eventStart": "2022-03-16T14:09:00",
          "eventStop": "2022-03-16T14:33:00",
          "duration": 24,
          "status": "Genuine",
          "associatedSiteId": 109665,
          "outfallName": "THORLEY ROAD BOULDNOR",
          "isImpacting": true,
          "overFlowSiteId": 110277,
          "historicSpillsList": []
        }
      ]
    },
    {
      "id": 344816723,
      "eventId": 570052,
      "siteUnitNumber": 12616,
      "bathingSite": "GURNARD",
      "eventStart": "2022-03-16T13:15:10",
      "eventStop": "2022-03-16T14:30:00",
      "duration": 74,
      "status": "Genuine",
      "associatedSiteId": 109700,
      "outfallName": "MARKET HILL COWES",
      "isImpacting": true,
      "overFlowSiteId": 0,
      "historicSpillsList": [
        {
          "id": 344816723,
          "eventId": 570052,
          "siteUnitNumber": 12616,
          "bathingSite": "GURNARD",
          "eventStart": "2022-03-16T13:15:10",
          "eventStop": "2022-03-16T14:30:00",
          "duration": 74,
          "status": "Genuine",
          "associatedSiteId": 109700,
          "outfallName": "MARKET HILL COWES",
          "isImpacting": true,
          "overFlowSiteId": 109299
        },
        {
          "id": 344816724,
          "eventId": 570052,
          "siteUnitNumber": 12617,
          "bathingSite": "COWES",
          "eventStart": "2022-03-16T13:15:10",
          "eventStop": "2022-03-16T14:30:00",
          "duration": 74,
          "status": "Genuine",
          "associatedSiteId": 109700,
          "outfallName": "MARKET HILL COWES",
          "isImpacting": true,
          "overFlowSiteId": 109299,
          "historicSpillsList": []
        }
      ]
    },
    {
      "id": 344815042,
      "eventId": 569901,
      "siteUnitNumber": 12615,
      "bathingSite": "COLWELL BAY",
      "eventStart": "2022-03-16T13:38:00",
      "eventStop": "2022-03-16T14:13:00",
      "duration": 35,
      "status": "Genuine",
      "associatedSiteId": 109663,
      "outfallName": "THE INSTITUTE YARMOUTH NO1",
      "isImpacting": true,
      "overFlowSiteId": 0,
      "historicSpillsList": [
        {
          "id": 344815042,
          "eventId": 569901,
          "siteUnitNumber": 12615,
          "bathingSite": "COLWELL BAY",
          "eventStart": "2022-03-16T13:38:00",
          "eventStop": "2022-03-16T14:13:00",
          "duration": 35,
          "status": "Genuine",
          "associatedSiteId": 109663,
          "outfallName": "THE INSTITUTE YARMOUTH NO1",
          "isImpacting": true,
          "overFlowSiteId": 108564
        }
      ]
    },
    {
      "id": 344828772,
      "eventId": 569790,
      "siteUnitNumber": 12568,
      "bathingSite": "SANDGATE",
      "eventStart": "2022-03-15T09:02:00",
      "eventStop": "2022-03-15T09:28:00",
      "duration": 26,
      "status": "Genuine",
      "associatedSiteId": 109897,
      "outfallName": "RANGE ROAD HYTHE K LONG",
      "isImpacting": true,
      "overFlowSiteId": 0,
      "historicSpillsList": [
        {
          "id": 344828772,
          "eventId": 569790,
          "siteUnitNumber": 12568,
          "bathingSite": "SANDGATE",
          "eventStart": "2022-03-15T09:02:00",
          "eventStop": "2022-03-15T09:28:00",
          "duration": 26,
          "status": "Genuine",
          "associatedSiteId": 109897,
          "outfallName": "RANGE ROAD HYTHE K LONG",
          "isImpacting": true,
          "overFlowSiteId": 116048
        },
        {
          "id": 344828773,
          "eventId": 569790,
          "siteUnitNumber": 12569,
          "bathingSite": "HYTHE",
          "eventStart": "2022-03-15T09:02:00",
          "eventStop": "2022-03-15T09:28:00",
          "duration": 26,
          "status": "Genuine",
          "associatedSiteId": 109897,
          "outfallName": "RANGE ROAD HYTHE K LONG",
          "isImpacting": true,
          "overFlowSiteId": 116048,
          "historicSpillsList": []
        }
      ]
    },
    {
      "id": 344824648,
      "eventId": 568966,
      "siteUnitNumber": 12548,
      "bathingSite": "TANKERTON",
      "eventStart": "2022-03-14T13:57:12",
      "eventStop": "2022-03-14T14:15:08",
      "duration": 17,
      "status": "Genuine",
      "associatedSiteId": 109830,
      "outfallName": "SWALECLIFFE NO1",
      "isImpacting": true,
      "overFlowSiteId": 0,
      "historicSpillsList": [
        {
          "id": 344824648,
          "eventId": 568966,
          "siteUnitNumber": 12548,
          "bathingSite": "TANKERTON",
          "eventStart": "2022-03-14T13:57:12",
          "eventStop": "2022-03-14T14:15:08",
          "duration": 17,
          "status": "Genuine",
          "associatedSiteId": 109830,
          "outfallName": "SWALECLIFFE NO1",
          "isImpacting": true,
          "overFlowSiteId": 115444
        },
        {
          "id": 344824649,
          "eventId": 568966,
          "siteUnitNumber": 12549,
          "bathingSite": "HERNE BAY CENTRAL",
          "eventStart": "2022-03-14T13:57:12",
          "eventStop": "2022-03-14T14:15:08",
          "duration": 17,
          "status": "Genuine",
          "associatedSiteId": 109830,
          "outfallName": "SWALECLIFFE NO1",
          "isImpacting": true,
          "overFlowSiteId": 115444,
          "historicSpillsList": []
        }
      ]
    },
    {
      "id": 344841823,
      "eventId": 568823,
      "siteUnitNumber": 12622,
      "bathingSite": "WHITECLIFF BAY",
      "eventStart": "2022-03-13T08:16:00",
      "eventStop": "2022-03-13T15:26:00",
      "duration": 430,
      "status": "Genuine",
      "associatedSiteId": 110096,
      "outfallName": "SANDOWN NO1",
      "isImpacting": true,
      "overFlowSiteId": 0,
      "historicSpillsList": [
        {
          "id": 344841823,
          "eventId": 568823,
          "siteUnitNumber": 12622,
          "bathingSite": "WHITECLIFF BAY",
          "eventStart": "2022-03-13T08:16:00",
          "eventStop": "2022-03-13T15:26:00",
          "duration": 430,
          "status": "Genuine",
          "associatedSiteId": 110096,
          "outfallName": "SANDOWN NO1",
          "isImpacting": true,
          "overFlowSiteId": 115453
        },
        {
          "id": 344841824,
          "eventId": 568823,
          "siteUnitNumber": 12623,
          "bathingSite": "YAVERLAND",
          "eventStart": "2022-03-13T08:16:00",
          "eventStop": "2022-03-13T15:26:00",
          "duration": 430,
          "status": "Genuine",
          "associatedSiteId": 110096,
          "outfallName": "SANDOWN NO1",
          "isImpacting": true,
          "overFlowSiteId": 115453,
          "historicSpillsList": []
        },
        {
          "id": 344841825,
          "eventId": 568823,
          "siteUnitNumber": 12624,
          "bathingSite": "SANDOWN",
          "eventStart": "2022-03-13T08:16:00",
          "eventStop": "2022-03-13T15:26:00",
          "duration": 430,
          "status": "Genuine",
          "associatedSiteId": 110096,
          "outfallName": "SANDOWN NO1",
          "isImpacting": true,
          "overFlowSiteId": 115453,
          "historicSpillsList": []
        }
      ]
    },
    {
      "id": 344830496,
      "eventId": 568552,
      "siteUnitNumber": 12576,
      "bathingSite": "ST LEONARDS",
      "eventStart": "2022-03-13T14:37:08",
      "eventStop": "2022-03-13T15:02:52",
      "duration": 25,
      "status": "Genuine",
      "associatedSiteId": 109903,
      "outfallName": "BEXHILL & HASTINGS NO2",
      "isImpacting": true,
      "overFlowSiteId": 0,
      "historicSpillsList": [
        {
          "id": 344830496,
          "eventId": 568552,
          "siteUnitNumber": 12576,
          "bathingSite": "ST LEONARDS",
          "eventStart": "2022-03-13T14:37:08",
          "eventStop": "2022-03-13T15:02:52",
          "duration": 25,
          "status": "Genuine",
          "associatedSiteId": 109903,
          "outfallName": "BEXHILL & HASTINGS NO2",
          "isImpacting": true,
          "overFlowSiteId": 115398
        },
        {
          "id": 344830497,
          "eventId": 568552,
          "siteUnitNumber": 12577,
          "bathingSite": "BEXHILL",
          "eventStart": "2022-03-13T14:37:08",
          "eventStop": "2022-03-13T15:02:52",
          "duration": 25,
          "status": "Genuine",
          "associatedSiteId": 109903,
          "outfallName": "BEXHILL & HASTINGS NO2",
          "isImpacting": true,
          "overFlowSiteId": 115398,
          "historicSpillsList": []
        }
      ]
    },
    {
      "id": 344821088,
      "eventId": 568824,
      "siteUnitNumber": 12617,
      "bathingSite": "COWES",
      "eventStart": "2022-03-13T03:45:00",
      "eventStop": "2022-03-13T13:42:00",
      "duration": 597,
      "status": "Genuine",
      "associatedSiteId": 109777,
      "outfallName": "APPLEY PARK RYDE TRANSFER",
      "isImpacting": true,
      "overFlowSiteId": 0,
      "historicSpillsList": [
        {
          "id": 344821088,
          "eventId": 568824,
          "siteUnitNumber": 12617,
          "bathingSite": "COWES",
          "eventStart": "2022-03-13T03:45:00",
          "eventStop": "2022-03-13T13:42:00",
          "duration": 597,
          "status": "Genuine",
          "associatedSiteId": 109777,
          "outfallName": "APPLEY PARK RYDE TRANSFER",
          "isImpacting": true,
          "overFlowSiteId": 108941
        },
        {
          "id": 344821089,
          "eventId": 568824,
          "siteUnitNumber": 12618,
          "bathingSite": "RYDE",
          "eventStart": "2022-03-13T03:45:00",
          "eventStop": "2022-03-13T13:42:00",
          "duration": 597,
          "status": "Genuine",
          "associatedSiteId": 109777,
          "outfallName": "APPLEY PARK RYDE TRANSFER",
          "isImpacting": true,
          "overFlowSiteId": 108941,
          "historicSpillsList": []
        }
      ]
    },
    {
      "id": 344814143,
      "eventId": 568472,
      "siteUnitNumber": 12616,
      "bathingSite": "GURNARD",
      "eventStart": "2022-03-13T10:59:00",
      "eventStop": "2022-03-13T11:02:00",
      "duration": 3,
      "status": "Genuine",
      "associatedSiteId": 109652,
      "outfallName": "WOODVALE TRANSFER NO1",
      "isImpacting": true,
      "overFlowSiteId": 0,
      "historicSpillsList": [
        {
          "id": 344814143,
          "eventId": 568472,
          "siteUnitNumber": 12616,
          "bathingSite": "GURNARD",
          "eventStart": "2022-03-13T10:59:00",
          "eventStop": "2022-03-13T11:02:00",
          "duration": 3,
          "status": "Genuine",
          "associatedSiteId": 109652,
          "outfallName": "WOODVALE TRANSFER NO1",
          "isImpacting": true,
          "overFlowSiteId": 115966
        },
        {
          "id": 344814144,
          "eventId": 568472,
          "siteUnitNumber": 12617,
          "bathingSite": "COWES",
          "eventStart": "2022-03-13T10:59:00",
          "eventStop": "2022-03-13T11:02:00",
          "duration": 3,
          "status": "Genuine",
          "associatedSiteId": 109652,
          "outfallName": "WOODVALE TRANSFER NO1",
          "isImpacting": true,
          "overFlowSiteId": 115966,
          "historicSpillsList": []
        }
      ]
    },
    {
      "id": 344814141,
      "eventId": 568822,
      "siteUnitNumber": 12616,
      "bathingSite": "GURNARD",
      "eventStart": "2022-03-13T08:35:00",
      "eventStop": "2022-03-13T08:40:00",
      "duration": 5,
      "status": "Genuine",
      "associatedSiteId": 109652,
      "outfallName": "WOODVALE TRANSFER NO1",
      "isImpacting": true,
      "overFlowSiteId": 0,
      "historicSpillsList": [
        {
          "id": 344814141,
          "eventId": 568822,
          "siteUnitNumber": 12616,
          "bathingSite": "GURNARD",
          "eventStart": "2022-03-13T08:35:00",
          "eventStop": "2022-03-13T08:40:00",
          "duration": 5,
          "status": "Genuine",
          "associatedSiteId": 109652,
          "outfallName": "WOODVALE TRANSFER NO1",
          "isImpacting": true,
          "overFlowSiteId": 115966
        },
        {
          "id": 344814142,
          "eventId": 568822,
          "siteUnitNumber": 12617,
          "bathingSite": "COWES",
          "eventStart": "2022-03-13T08:35:00",
          "eventStop": "2022-03-13T08:40:00",
          "duration": 5,
          "status": "Genuine",
          "associatedSiteId": 109652,
          "outfallName": "WOODVALE TRANSFER NO1",
          "isImpacting": true,
          "overFlowSiteId": 115966,
          "historicSpillsList": []
        }
      ]
    },
    {
      "id": 344841833,
      "eventId": 568287,
      "siteUnitNumber": 12623,
      "bathingSite": "YAVERLAND",
      "eventStart": "2022-03-13T05:00:00",
      "eventStop": "2022-03-13T07:56:00",
      "duration": 176,
      "status": "Genuine",
      "associatedSiteId": 110096,
      "outfallName": "SANDOWN NO1",
      "isImpacting": true,
      "overFlowSiteId": 0,
      "historicSpillsList": [
        {
          "id": 344841833,
          "eventId": 568287,
          "siteUnitNumber": 12623,
          "bathingSite": "YAVERLAND",
          "eventStart": "2022-03-13T05:00:00",
          "eventStop": "2022-03-13T07:56:00",
          "duration": 176,
          "status": "Genuine",
          "associatedSiteId": 110096,
          "outfallName": "SANDOWN NO1",
          "isImpacting": true,
          "overFlowSiteId": 115453
        },
        {
          "id": 344841834,
          "eventId": 568287,
          "siteUnitNumber": 12624,
          "bathingSite": "SANDOWN",
          "eventStart": "2022-03-13T05:00:00",
          "eventStop": "2022-03-13T07:56:00",
          "duration": 176,
          "status": "Genuine",
          "associatedSiteId": 110096,
          "outfallName": "SANDOWN NO1",
          "isImpacting": true,
          "overFlowSiteId": 115453,
          "historicSpillsList": []
        },
        {
          "id": 344841840,
          "eventId": 568287,
          "siteUnitNumber": 12622,
          "bathingSite": "WHITECLIFF BAY",
          "eventStart": "2022-03-13T05:00:00",
          "eventStop": "2022-03-13T07:56:00",
          "duration": 176,
          "status": "Genuine",
          "associatedSiteId": 110096,
          "outfallName": "SANDOWN NO1",
          "isImpacting": true,
          "overFlowSiteId": 115453,
          "historicSpillsList": []
        }
      ]
    },
    {
      "id": 344817953,
      "eventId": 568273,
      "siteUnitNumber": 12616,
      "bathingSite": "GURNARD",
      "eventStart": "2022-03-13T04:43:51",
      "eventStop": "2022-03-13T06:10:00",
      "duration": 86,
      "status": "Genuine",
      "associatedSiteId": 109705,
      "outfallName": "SPRINGHILL COWES TRANSFER",
      "isImpacting": true,
      "overFlowSiteId": 0,
      "historicSpillsList": [
        {
          "id": 344817953,
          "eventId": 568273,
          "siteUnitNumber": 12616,
          "bathingSite": "GURNARD",
          "eventStart": "2022-03-13T04:43:51",
          "eventStop": "2022-03-13T06:10:00",
          "duration": 86,
          "status": "Genuine",
          "associatedSiteId": 109705,
          "outfallName": "SPRINGHILL COWES TRANSFER",
          "isImpacting": true,
          "overFlowSiteId": 108943
        },
        {
          "id": 344817954,
          "eventId": 568273,
          "siteUnitNumber": 12617,
          "bathingSite": "COWES",
          "eventStart": "2022-03-13T04:43:51",
          "eventStop": "2022-03-13T06:10:00",
          "duration": 86,
          "status": "Genuine",
          "associatedSiteId": 109705,
          "outfallName": "SPRINGHILL COWES TRANSFER",
          "isImpacting": true,
          "overFlowSiteId": 108943,
          "historicSpillsList": []
        }
      ]
    },
    {
      "id": 344814145,
      "eventId": 568189,
      "siteUnitNumber": 12616,
      "bathingSite": "GURNARD",
      "eventStart": "2022-03-13T02:26:00",
      "eventStop": "2022-03-13T06:00:00",
      "duration": 214,
      "status": "Genuine",
      "associatedSiteId": 109652,
      "outfallName": "WOODVALE TRANSFER NO1",
      "isImpacting": true,
      "overFlowSiteId": 0,
      "historicSpillsList": [
        {
          "id": 344814145,
          "eventId": 568189,
          "siteUnitNumber": 12616,
          "bathingSite": "GURNARD",
          "eventStart": "2022-03-13T02:26:00",
          "eventStop": "2022-03-13T06:00:00",
          "duration": 214,
          "status": "Genuine",
          "associatedSiteId": 109652,
          "outfallName": "WOODVALE TRANSFER NO1",
          "isImpacting": true,
          "overFlowSiteId": 115966
        },
        {
          "id": 344814146,
          "eventId": 568189,
          "siteUnitNumber": 12617,
          "bathingSite": "COWES",
          "eventStart": "2022-03-13T02:26:00",
          "eventStop": "2022-03-13T06:00:00",
          "duration": 214,
          "status": "Genuine",
          "associatedSiteId": 109652,
          "outfallName": "WOODVALE TRANSFER NO1",
          "isImpacting": true,
          "overFlowSiteId": 115966,
          "historicSpillsList": []
        }
      ]
    },
    {
      "id": 344852568,
      "eventId": 568428,
      "siteUnitNumber": 12615,
      "bathingSite": "COLWELL BAY",
      "eventStart": "2022-03-13T01:59:00",
      "eventStop": "2022-03-13T05:02:00",
      "duration": 183,
      "status": "Genuine",
      "associatedSiteId": 115498,
      "outfallName": "NORTON TRANSFER IOW",
      "isImpacting": true,
      "overFlowSiteId": 0,
      "historicSpillsList": [
        {
          "id": 344852568,
          "eventId": 568428,
          "siteUnitNumber": 12615,
          "bathingSite": "COLWELL BAY",
          "eventStart": "2022-03-13T01:59:00",
          "eventStop": "2022-03-13T05:02:00",
          "duration": 183,
          "status": "Genuine",
          "associatedSiteId": 115498,
          "outfallName": "NORTON TRANSFER IOW",
          "isImpacting": true,
          "overFlowSiteId": 108544
        },
        {
          "id": 344852569,
          "eventId": 568428,
          "siteUnitNumber": 12614,
          "bathingSite": "TOTLAND BAY",
          "eventStart": "2022-03-13T01:59:00",
          "eventStop": "2022-03-13T05:02:00",
          "duration": 183,
          "status": "Genuine",
          "associatedSiteId": 115498,
          "outfallName": "NORTON TRANSFER IOW",
          "isImpacting": true,
          "overFlowSiteId": 108544,
          "historicSpillsList": []
        }
      ]
    }
  ]
}